denser_retriever/__init__.py
denser_retriever/embeddings.py
denser_retriever/filter.py
denser_retriever/gradient_boost.py
denser_retriever/keyword.py
denser_retriever/reranker.py
denser_retriever/retriever.py
denser_retriever/utils.py
denser_retriever/vectordb/__init__.py
denser_retriever/vectordb/base.py
denser_retriever/vectordb/milvus.py
denser_retriever-0.1.3.dist-info/LICENSE
denser_retriever-0.1.3.dist-info/METADATA
denser_retriever-0.1.3.dist-info/WHEEL
denser_retriever-0.1.3.dist-info/entry_points.txt
denser_retriever-0.1.3.dist-info/RECORD
