Metadata-Version: 2.1
Name: denser-retriever
Version: 0.1.3
Summary: Enterprise-grade AI retriever solution that seamlessly integrates to enhance your AI applications.
Home-page: https://github.com/denser-org/denser-retriever
License: MIT
Author: denser-org
Author-email: support@denser.ai
Requires-Python: >=3.10.0,<4.0.0
Classifier: Development Status :: 3 - Alpha
Classifier: Intended Audience :: Developers
Classifier: License :: OSI Approved :: MIT License
Classifier: Operating System :: OS Independent
Classifier: Programming Language :: Python :: 3
Classifier: Programming Language :: Python :: 3.10
Classifier: Programming Language :: Python :: 3.11
Classifier: Programming Language :: Python :: 3.12
Classifier: Topic :: Software Development :: Libraries :: Python Modules
Requires-Dist: beautifulsoup4 (>=4.12.3,<5.0.0)
Requires-Dist: datasets (>=2.18.0,<3.0.0)
Requires-Dist: elasticsearch (>=8.13.0,<9.0.0)
Requires-Dist: fake_useragent (>=1.5.1,<2.0.0)
Requires-Dist: langchain-community (>=0.2.0,<0.3.0)
Requires-Dist: langchain-core (==0.2.10)
Requires-Dist: langchain-elasticsearch (>=0.2.2,<0.3.0)
Requires-Dist: langchain-huggingface (>=0.0.3,<0.0.4)
Requires-Dist: langchain-milvus (>=0.1.1,<0.2.0)
Requires-Dist: langchain-qdrant (>=0.1.2,<0.2.0)
Requires-Dist: langchain-text-splitters (>=0.2.2,<0.3.0)
Requires-Dist: numpy (>=1.26.4,<2.0.0)
Requires-Dist: pydantic-settings (>=2.2.1,<3.0.0)
Requires-Dist: pydantic[dotenv] (>=2.7.1,<3.0.0)
Requires-Dist: pymilvus (>=2.4.4,<3.0.0)
Requires-Dist: pypdf (>=4.2.0,<5.0.0)
Requires-Dist: pytrec-eval (>=0.5,<0.6)
Requires-Dist: rich (>=10.14.0,<11.0.0)
Requires-Dist: sentence-transformers (>=2.7.0,<3.0.0)
Requires-Dist: torch (>=1.13.1,<2.0.0)
Requires-Dist: typer[all] (>=0.12.1,<0.13.0)
Requires-Dist: xgboost (>=2.0.3,<3.0.0)
Project-URL: Repository, https://github.com/denser-org/denser-retriever
